{
  "descriptionHash": "88A6A814C6353DB64EECAE4A601ADD14174E8A5C2E679BBC7C4A98C81EE5FE4BC7F11E6108D6CCF72C959F8F3AD33DFF538FDC4874370D13F8F2BC3A4960321D",
  "descriptionLocation": "../api_v2.json",
  "lockFileVersion": "1.0.0",
  "kiotaVersion": "1.28.0",
  "clientClassName": "InstantlyOpenApiClient",
  "typeAccessModifier": "Public",
  "clientNamespaceName": "Soenneker.Instantly.OpenApiClient",
  "language": "CSharp",
  "usesBackingStore": false,
  "excludeBackwardCompatible": true,
  "includeAdditionalData": true,
  "disableSSLValidation": false,
  "serializers": [
    "Microsoft.Kiota.Serialization.Json.JsonSerializationWriterFactory",
    "Microsoft.Kiota.Serialization.Text.TextSerializationWriterFactory",
    "Microsoft.Kiota.Serialization.Form.FormSerializationWriterFactory",
    "Microsoft.Kiota.Serialization.Multipart.MultipartSerializationWriterFactory"
  ],
  "deserializers": [
    "Microsoft.Kiota.Serialization.Json.JsonParseNodeFactory",
    "Microsoft.Kiota.Serialization.Text.TextParseNodeFactory",
    "Microsoft.Kiota.Serialization.Form.FormParseNodeFactory"
  ],
  "structuredMimeTypes": [
    "application/json",
    "text/plain;q=0.9",
    "application/x-www-form-urlencoded;q=0.2",
    "multipart/form-data;q=0.1"
  ],
  "includePatterns": [],
  "excludePatterns": [],
  "disabledValidationRules": []
}