{
  "descriptionHash": "63E99D1EAFF5D40EAC4106BE4A7AA6FCEDF91D7BA396C25D1FF24E5318151567022B13691B8BD95D2993F651F70E46E09F4DF7F800AB9A2B2C186AB5FE38A3CD",
  "descriptionLocation": "../../api_v2.json",
  "lockFileVersion": "1.0.0",
  "kiotaVersion": "1.30.0",
  "clientClassName": "InstantlyOpenApiClient",
  "typeAccessModifier": "Public",
  "clientNamespaceName": "Soenneker.Instantly.OpenApiClient",
  "language": "CSharp",
  "usesBackingStore": false,
  "excludeBackwardCompatible": true,
  "includeAdditionalData": true,
  "disableSSLValidation": false,
  "serializers": [
    "Microsoft.Kiota.Serialization.Json.JsonSerializationWriterFactory",
    "Microsoft.Kiota.Serialization.Text.TextSerializationWriterFactory",
    "Microsoft.Kiota.Serialization.Form.FormSerializationWriterFactory",
    "Microsoft.Kiota.Serialization.Multipart.MultipartSerializationWriterFactory"
  ],
  "deserializers": [
    "Microsoft.Kiota.Serialization.Json.JsonParseNodeFactory",
    "Microsoft.Kiota.Serialization.Text.TextParseNodeFactory",
    "Microsoft.Kiota.Serialization.Form.FormParseNodeFactory"
  ],
  "structuredMimeTypes": [
    "application/json",
    "text/plain;q=0.9",
    "application/x-www-form-urlencoded;q=0.2",
    "multipart/form-data;q=0.1"
  ],
  "includePatterns": [],
  "excludePatterns": [],
  "disabledValidationRules": []
}